<?xml version="1.0" encoding="utf-8" ?>
<dwsync>
<file name="arequipa-la-ciudad-blanca.blade.php" server="ftp.happyperutours.com" local="133147425028650568" remote="133251865800000000" Dst="0" />
<file name="ciudad-de-ica.blade.php" server="ftp.happyperutours.com" local="133147425494589775" remote="133251865800000000" Dst="0" />
<file name="ciudad-de-pisco.blade.php" server="ftp.happyperutours.com" local="133147425699816942" remote="133251865800000000" Dst="0" />
<file name="la-ciudad-de-puno.blade.php" server="ftp.happyperutours.com" local="133147425299078200" remote="133251865800000000" Dst="0" />
<file name="cusco-ombligo-del-mundo.blade.php" server="ftp.happyperutours.com" local="133147424583711737" remote="133251865800000000" Dst="0" />
<file name="lima-ciudad-de-reyes.blade.php" server="ftp.happyperutours.com" local="133147424838251856" remote="133251865800000000" Dst="0" />
<file name="puerto-maldonado.blade.php" server="ftp.happyperutours.com" local="133147425924375897" remote="133251865800000000" Dst="0" />
<file name="arequipa-la-ciudad-blanca.blade.php" server="15.204.142.117" local="133271143436081152" remote="133271328000000000" Dst="0" />
<file name="ciudad-de-ica.blade.php" server="15.204.142.117" local="133271143590568605" remote="133271328000000000" Dst="0" />
<file name="ciudad-de-pisco.blade.php" server="15.204.142.117" local="133271143715215917" remote="133271328000000000" Dst="0" />
<file name="cusco-ombligo-del-mundo.blade.php" server="15.204.142.117" local="133271143835934213" remote="133271328000000000" Dst="0" />
<file name="la-ciudad-de-puno.blade.php" server="15.204.142.117" local="133271143979119402" remote="133271328000000000" Dst="0" />
<file name="lima-ciudad-de-reyes.blade.php" server="15.204.142.117" local="133271144094841103" remote="133271328000000000" Dst="0" />
<file name="puerto-maldonado.blade.php" server="15.204.142.117" local="133271144235235713" remote="133271328000000000" Dst="0" />
<file name="arequipa-la-ciudad-blanca.blade.php" server="65.181.111.146" local="133658798420925846" remote="133658983800000000" Dst="0" />
<file name="ciudad-de-ica.blade.php" server="65.181.111.146" local="133658799315485507" remote="133658983800000000" Dst="0" />
<file name="ciudad-de-pisco.blade.php" server="65.181.111.146" local="133658799477255331" remote="133658983800000000" Dst="0" />
<file name="cusco-ombligo-del-mundo.blade.php" server="65.181.111.146" local="133658798033071290" remote="133658983800000000" Dst="0" />
<file name="la-ciudad-de-puno.blade.php" server="65.181.111.146" local="133658799599072327" remote="133658983800000000" Dst="0" />
<file name="lima-ciudad-de-reyes.blade.php" server="65.181.111.146" local="133658799694872905" remote="133658983800000000" Dst="0" />
<file name="puerto-maldonado.blade.php" server="65.181.111.146" local="133658803406713608" remote="133658983800000000" Dst="0" />
</dwsync>